maxminddb-stubs/METADATA.toml
maxminddb-stubs/__init__.pyi
maxminddb-stubs/compat.pyi
maxminddb-stubs/const.pyi
maxminddb-stubs/decoder.pyi
maxminddb-stubs/errors.pyi
maxminddb-stubs/extension.pyi
maxminddb-stubs/reader.pyi
types_maxminddb-1.5.0.dist-info/METADATA
types_maxminddb-1.5.0.dist-info/WHEEL
types_maxminddb-1.5.0.dist-info/top_level.txt
types_maxminddb-1.5.0.dist-info/RECORD
