Metadata-Version: 2.1
Name: types-maxminddb
Version: 1.5.0
Summary: Typing stubs for maxminddb
Home-page: https://github.com/python/typeshed
License: Apache-2.0 license
Platform: UNKNOWN
Classifier: License :: OSI Approved :: Apache Software License
Classifier: Typing :: Typed
